tenetan/__init__.py
tenetan/centrality/__init__.py
tenetan/centrality/eigenvector/__init__.py
tenetan/centrality/eigenvector/eigenvector.py
tenetan/centrality/eigenvector/layer_similarity.py
tenetan/community/__init__.py
tenetan/community/multi/__init__.py
tenetan/community/multi/dompla.py
tenetan/community/multi/parafac.py
tenetan/community/single/__init__.py
tenetan/community/single/temp_louvain.py
tenetan/networks/__init__.py
tenetan/networks/snapshot.py
tenetan/state/__init__.py
tenetan/state/state.py
tenetan/static/__init__.py
tenetan/static/centrality.py
tenetan/static/distance.py
tenetan/static/linalg.py
tenetan-0.8.0.dist-info/LICENSE
tenetan-0.8.0.dist-info/METADATA
tenetan-0.8.0.dist-info/WHEEL
tenetan-0.8.0.dist-info/top_level.txt
tenetan-0.8.0.dist-info/RECORD
