Metadata-Version: 2.2
Name: tenetan
Version: 0.8.0
Summary: Temporal Network Analysis Library
Author-email: Alexander Bakhtin <alexander.bakhtin@protonmail.com>
License:                     GNU GENERAL PUBLIC LICENSE
Project-URL: Homepage, https://github.com/bakhtos/tenetan
Keywords: networks,graphs,temporal networks,temporal graphs,complex networks,time-evolving networks
Classifier: Development Status :: 2 - Pre-Alpha
Classifier: Intended Audience :: Education
Classifier: Intended Audience :: Science/Research
Classifier: License :: OSI Approved :: GNU General Public License v3 (GPLv3)
Classifier: Programming Language :: Python :: 3
Classifier: Programming Language :: Python :: 3.10
Classifier: Topic :: Scientific/Engineering :: Mathematics
Requires-Python: >=3.10
License-File: LICENSE
Requires-Dist: tensorly==0.8.1
Requires-Dist: TLViz==0.1.1
Requires-Dist: scipy
Requires-Dist: statsmodels>=0.12.0
Requires-Dist: networkx
